home_connect_sdk/__init__.py
home_connect_sdk/api_client.py
home_connect_sdk/configuration.py
home_connect_sdk/exceptions.py
home_connect_sdk/rest.py
home_connect_sdk/api/__init__.py
home_connect_sdk/api/commands_api.py
home_connect_sdk/api/default_api.py
home_connect_sdk/api/images_api.py
home_connect_sdk/api/programs_api.py
home_connect_sdk/api/settings_api.py
home_connect_sdk/api/status_events_api.py
home_connect_sdk/models/__init__.py
home_connect_sdk/models/active_program_not_set_error.py
home_connect_sdk/models/array_of_available_programs.py
home_connect_sdk/models/array_of_available_programs_data.py
home_connect_sdk/models/array_of_available_programs_data_constraints.py
home_connect_sdk/models/array_of_available_programs_data_programs.py
home_connect_sdk/models/array_of_events.py
home_connect_sdk/models/array_of_events_items.py
home_connect_sdk/models/array_of_home_appliances.py
home_connect_sdk/models/array_of_home_appliances_data.py
home_connect_sdk/models/array_of_home_appliances_data_homeappliances.py
home_connect_sdk/models/array_of_images.py
home_connect_sdk/models/array_of_images_data.py
home_connect_sdk/models/array_of_images_data_images.py
home_connect_sdk/models/array_of_options.py
home_connect_sdk/models/array_of_options_data.py
home_connect_sdk/models/array_of_programs.py
home_connect_sdk/models/array_of_programs_data.py
home_connect_sdk/models/array_of_programs_data_constraints.py
home_connect_sdk/models/array_of_programs_data_programs.py
home_connect_sdk/models/array_of_settings.py
home_connect_sdk/models/array_of_settings_data.py
home_connect_sdk/models/array_of_settings_data_settings.py
home_connect_sdk/models/array_of_status.py
home_connect_sdk/models/array_of_status_data.py
home_connect_sdk/models/command.py
home_connect_sdk/models/command_data.py
home_connect_sdk/models/command_definition.py
home_connect_sdk/models/command_definition_data.py
home_connect_sdk/models/conflict.py
home_connect_sdk/models/conflict_error.py
home_connect_sdk-1.0.0.dist-info/METADATA
home_connect_sdk-1.0.0.dist-info/WHEEL
home_connect_sdk-1.0.0.dist-info/top_level.txt
home_connect_sdk-1.0.0.dist-info/RECORD
